.travis.yml
CHANGELOG.rst
CONTRIBUTORS.rst
MANIFEST.in
Makefile
README.rst
requirements-test.txt
requirements.txt
setup.py
tox.ini
smwogger/__init__.py
smwogger/api.py
smwogger/cli.py
smwogger/main.py
smwogger/smoketest.py
smwogger/util.py
smwogger.egg-info/PKG-INFO
smwogger.egg-info/SOURCES.txt
smwogger.egg-info/dependency_links.txt
smwogger.egg-info/entry_points.txt
smwogger.egg-info/not-zip-safe
smwogger.egg-info/requires.txt
smwogger.egg-info/top_level.txt
smwogger/tests/__init__.py
smwogger/tests/petstore.py
smwogger/tests/scenario.py
smwogger/tests/service.py
smwogger/tests/support.py
smwogger/tests/test_api.py
smwogger/tests/test_main.py