Metadata-Version: 1.0
Name: smwogger
Version: 1.0
Summary: Smoke Test tool
Home-page: https://github.com/tarekziade/smwogger
Author: Tarek Ziade
Author-email: tarek@ziade.org
License: UNKNOWN
Platform: UNKNOWN
